distinctiveness/__init__.py
distinctiveness/dc.py
distinctiveness/test.py
distinctiveness-0.14.6.dist-info/LICENSE
distinctiveness-0.14.6.dist-info/METADATA
distinctiveness-0.14.6.dist-info/WHEEL
distinctiveness-0.14.6.dist-info/top_level.txt
distinctiveness-0.14.6.dist-info/RECORD
