Metadata-Version: 2.1
Name: distinctiveness
Version: 0.14.6
Summary: A Python package to calculate Distinctiveness Centrality
Home-page: https://github.com/iandreafc/distinctiveness
Author: Andrea Fronzetti Colladon
License: MIT
Platform: UNKNOWN
Classifier: Programming Language :: Python :: 3
Classifier: License :: OSI Approved :: MIT License
Classifier: Operating System :: OS Independent
Requires-Python: >=3.6
Requires-Dist: networkx
Requires-Dist: numpy
Requires-Dist: pandas
